{
    "parameters": {
        "Testing_Randome": 0.0008,
        "Total_Infection_coefficient": 1.94688610435758e-06,
        "Normal_death_rate_constant_0": 3.29e-05,
        "Corona_death_rate_constant": 0.002,
        "Birth_rate": 3.29e-05,
        "Testing_for_Symptoms": 500.0,
        "Corona_recover": 0.067,
        "Symptoms_appear": 0.30165,
        "Infection_from_non_tested_no_symptoms_0": 0.508,
        "Infection_from_non_tested_symptoms": 0.25,
        "Infection_from_tested_no_symptoms_0": 0.025,
        "Infection_from_tested_symptoms": 0.025,
        "Social_Distance": 534700.0,
        "Government_induced_isolation_factor_0": 10.0,
        "Time_government_action_0": 15.0,
        "lockdown_duration": 7.0,
        "lockdownPause_duration_0": 7.0,
        "n_lockdowns": 0.0,
        "n_pauses": 0.0,
        "intermittent_time": 0.0,
        "timeFraction_lockdown_0": 0.55,
        "number_cutoff": 0.0,
        "symptomatic_numberTolerance_0": 141.0,
        "governmentResponseFactorToDiagnosedInfected_0": 0.0,
        "social_distancing_factor": 10.0,
        "Social_Distance_base": 534700.0,
        "default": 1.0
    }
}