{"initials":{"Hospitalized":{"name":"Hospitalized","identifiers":{"ncit":"C25179","biomodels.species":"BIOMD0000000960:Hospitalized","ido":"0000511"},"value":0.0,"context":{}},"Asymptomatic":{"name":"Asymptomatic","identifiers":{"ncit":"C171133","biomodels.species":"BIOMD0000000960:Asymptomatic","ido":"0000569"},"value":2196.0,"context":{}},"Exposed":{"name":"Exposed","identifiers":{"ncit":"C171133","biomodels.species":"BIOMD0000000960:Exposed","ido":"0000597"},"value":36600.0,"context":{}},"Deceased":{"name":"Deceased","identifiers":{"ncit":"C171133","biomodels.species":"BIOMD0000000960:Deceased"},"value":0.0,"context":{}},"Recovered":{"name":"Recovered","identifiers":{"ncit":"C171133","biomodels.species":"BIOMD0000000960:Recovered","ido":"0000621"},"value":0.0,"context":{}},"Susceptible":{"name":"Susceptible","identifiers":{"ncit":"C171133","biomodels.species":"BIOMD0000000960:Susceptible","ido":"0000514"},"value":9.9e6,"context":{}},"Infectious":{"name":"Infectious","identifiers":{"ncit":"C171133","biomodels.species":"BIOMD0000000960:Infectious","ido":"0000511"},"value":732.0,"context":{}}}}