{"parameters":{"sigma":{"name":"sigma","identifiers":{},"value":0.18916936341960056,"context":{}},"omega":{"name":"omega","identifiers":{},"value":0.79720271935763,"context":{}},"gamma":{"name":"gamma","identifiers":{},"value":0.4065992453466051,"context":{}},"t1":{"name":"(('Susceptible', ('identity', 'ido:0000514')), ('Exposed', ('identity', 'ido:0000514'), ('identity', 'ncit:C171133'), ('property', 'ido:0000597')), ('Total_population', ('Infected', ('identity', 'ido:0000511'), ('identity', 'ncit:C171133'))), 'GroupedControlledConversion', 'rate')","identifiers":{},"value":0.5102705823777182,"context":{}}}}