{"initials":{"Super_spreaders":{"name":"Super_spreaders","identifiers":{"ncit":"C49508","biomodels.species":"BIOMD0000000958:Super_spreaders","ido":"0000463"},"value":0.05847268110799781,"context":{}},"Fatalities":{"name":"Fatalities","identifiers":{"ncit":"C28554","biomodels.species":"BIOMD0000000958:Fatalities"},"value":0.2153739772598915,"context":{}},"Asymptomatic":{"name":"Asymptomatic","identifiers":{"ncit":"C171133","biomodels.species":"BIOMD0000000958:Asymptomatic","ido":"0000569"},"value":0.18106387853498154,"context":{}},"Exposed":{"name":"Exposed","identifiers":{"ncit":"C171133","biomodels.species":"BIOMD0000000958:Exposed","ido":"0000597"},"value":0.043372310969565966,"context":{}},"Recovered":{"name":"Recovered","identifiers":{"ncit":"C171133","biomodels.species":"BIOMD0000000958:Recovered"},"value":0.11276925611654168,"context":{}},"Susceptible":{"name":"Susceptible","identifiers":{"ncit":"C171133","biomodels.species":"BIOMD0000000958:Susceptible","ido":"0000514"},"value":0.13904275760156917,"context":{}},"Infectious":{"name":"Infectious","identifiers":{"ncit":"C171549","biomodels.species":"BIOMD0000000958:Infectious","ido":"0000511"},"value":0.22287089268369967,"context":{}},"Hospitalised":{"name":"Hospitalised","identifiers":{"ncit":"C25179","biomodels.species":"BIOMD0000000958:Hospitalised"},"value":0.02703424572575272,"context":{}}}}